wespy/__init__.py
wespy/__main__.py
wespy/juejin.py
wespy/main.py
wespy-0.1.5.dist-info/licenses/LICENSE
wespy-0.1.5.dist-info/METADATA
wespy-0.1.5.dist-info/WHEEL
wespy-0.1.5.dist-info/entry_points.txt
wespy-0.1.5.dist-info/top_level.txt
wespy-0.1.5.dist-info/RECORD
