Metadata-Version: 2.4
Name: wespy
Version: 0.1.5
Summary: A Python tool for fetching web articles and converting them to Markdown format
Home-page: https://github.com/tianchangNorth/WeSpy
Author: tianchang
Author-email: 
License: MIT
Project-URL: Homepage, https://github.com/tianchangNorth/WeSpy
Project-URL: Bug Reports, https://github.com/tianchangNorth/WeSpy/issues
Project-URL: Source, https://github.com/tianchangNorth/WeSpy
Keywords: web scraping,article extraction,markdown converter,weixin
Classifier: Development Status :: 3 - Alpha
Classifier: Intended Audience :: Developers
Classifier: Topic :: Internet :: WWW/HTTP :: Browsers
Classifier: Topic :: Text Processing :: Markup :: HTML
Classifier: License :: OSI Approved :: MIT License
Classifier: Programming Language :: Python :: 3
Classifier: Programming Language :: Python :: 3.6
Classifier: Programming Language :: Python :: 3.7
Classifier: Programming Language :: Python :: 3.8
Classifier: Programming Language :: Python :: 3.9
Classifier: Programming Language :: Python :: 3.10
Classifier: Programming Language :: Python :: 3.11
Classifier: Operating System :: OS Independent
Requires-Python: >=3.6
License-File: LICENSE
Requires-Dist: requests>=2.20.0
Requires-Dist: beautifulsoup4>=4.9.0
Dynamic: home-page
Dynamic: license-file
Dynamic: requires-python
